weewx_orm/__init__.py
weewx_orm/archive_schema.py
weewx_orm-1.1.0.dist-info/DESCRIPTION.rst
weewx_orm-1.1.0.dist-info/METADATA
weewx_orm-1.1.0.dist-info/RECORD
weewx_orm-1.1.0.dist-info/WHEEL
weewx_orm-1.1.0.dist-info/metadata.json
weewx_orm-1.1.0.dist-info/top_level.txt
