Metadata-Version: 2.0
Name: weewx-orm
Version: 1.1.0
Summary: A library for interfacing with the Weewx database layer.
Home-page: https://github.com/beasley-weather/weewx-orm
Author: francium
Author-email: UNKNOWN
License: MIT
Platform: UNKNOWN
Requires-Dist: marshmallow-sqlalchemy
Requires-Dist: sqlalchemy
Requires-Dist: sqlalchemy-utils
